stop_iter/__init__.py
stop_iter-0.2.4.dist-info/LICENSE
stop_iter-0.2.4.dist-info/METADATA
stop_iter-0.2.4.dist-info/WHEEL
stop_iter-0.2.4.dist-info/RECORD
