Metadata-Version: 2.1
Name: stop-iter
Version: 0.2.4
Summary: An interuptable iterator for Python
License: Apache-2.0
Author: Cristian Garcia
Author-email: cgarcia.e88@gmail.com
Requires-Python: >=3.7,<4.0
Classifier: License :: OSI Approved :: Apache Software License
Classifier: Programming Language :: Python :: 3
Classifier: Programming Language :: Python :: 3.7
Classifier: Programming Language :: Python :: 3.8
Classifier: Programming Language :: Python :: 3.9
Classifier: Programming Language :: Python :: 3.10
Classifier: Programming Language :: Python :: 3.11
Classifier: Programming Language :: Python :: 3.12
